{"LS0065":{"name":"LS0065","payment":false},"Mansion0056":{"name":"Mansion0056","payment":false},"LS0011":{"name":"LS0011","payment":false},"Beach0063":{"name":"Beach0063","payment":false},"Trailer0084":{"name":"Trailer0084","payment":false},"LS0009":{"name":"LS0009","payment":false},"Ghetto0048":{"name":"Ghetto0048","payment":false},"Trailer0022":{"name":"Trailer0022","payment":false},"Mansion0190":{"name":"Mansion0190","payment":false},"Beach0061":{"name":"Beach0061","payment":false},"Mansion0010":{"name":"Mansion0010","payment":false},"Mansion0181":{"name":"Mansion0181","payment":false},"Mansion0241":{"name":"Mansion0241","payment":false},"Mansion0022":{"name":"Mansion0022","payment":false},"Mansion0061":{"name":"Mansion0061","payment":false},"Beach0080":{"name":"Beach0080","payment":false},"LS0028":{"name":"LS0028","payment":false},"Ghetto0040":{"name":"Ghetto0040","payment":false},"LS0018":{"name":"LS0018","payment":false},"LS0001":{"name":"LS0001","payment":false},"Mansion0064":{"name":"Mansion0064","payment":false},"Mansion0058":{"name":"Mansion0058","payment":false},"Mansion0186":{"name":"Mansion0186","payment":false},"Trailer0038":{"name":"Trailer0038","payment":false},"LS0030":{"name":"LS0030","payment":false},"Beach0057":{"name":"Beach0057","payment":false},"Beach0060":{"name":"Beach0060","payment":false},"Mansion0073":{"name":"Mansion0073","payment":false},"Beach0064":{"name":"Beach0064","payment":false},"Trailer0017":{"name":"Trailer0017","payment":false},"Mansion0184":{"name":"Mansion0184","payment":false},"Mansion0224":{"name":"Mansion0224","payment":false},"Mansion0067":{"name":"Mansion0067","payment":false},"LS0010":{"name":"LS0010","payment":false},"Mansion0020":{"name":"Mansion0020","payment":false},"Mansion0180":{"name":"Mansion0180","payment":false},"Mansion0084":{"name":"Mansion0084","payment":false},"Paleto0018":{"name":"Paleto0018","payment":false},"Rancho0004":{"name":"Rancho0004","payment":false},"LS0012":{"name":"LS0012","payment":false},"Beach0079":{"name":"Beach0079","payment":false},"Mansion0182":{"name":"Mansion0182","payment":false}}